tugit/Installer.py
tugit/__init__.py
tugit-1.1.2.dist-info/LICENSE
tugit-1.1.2.dist-info/METADATA
tugit-1.1.2.dist-info/WHEEL
tugit-1.1.2.dist-info/top_level.txt
tugit-1.1.2.dist-info/RECORD
